scrapy_redis_bf/__init__.py
scrapy_redis_bf/defaults.py
scrapy_redis_bf/dupefilter.py
scrapy_redis_bf/exception.py
scrapy_redis_bf/scheduler.py
scrapy_redis_bf-0.1.2.dist-info/METADATA
scrapy_redis_bf-0.1.2.dist-info/WHEEL
scrapy_redis_bf-0.1.2.dist-info/licenses/LICENSE
scrapy_redis_bf-0.1.2.dist-info/RECORD
